pixaris/__init__.py
pixaris/data_loaders/__init__.py
pixaris/data_loaders/base.py
pixaris/data_loaders/gcp.py
pixaris/data_loaders/local.py
pixaris/experiment_handlers/__init__.py
pixaris/experiment_handlers/base.py
pixaris/experiment_handlers/gcp.py
pixaris/experiment_handlers/local.py
pixaris/feedback_handlers/__init__.py
pixaris/feedback_handlers/base.py
pixaris/feedback_handlers/gcp.py
pixaris/feedback_handlers/local.py
pixaris/frontend/main.py
pixaris/frontend/tab_experiment_tracking.py
pixaris/frontend/tab_feedback.py
pixaris/generation/__init__.py
pixaris/generation/base.py
pixaris/generation/comfyui.py
pixaris/generation/comfyui_cluster.py
pixaris/generation/comfyui_utils/workflow.py
pixaris/generation/flux.py
pixaris/generation/gemini.py
pixaris/generation/imagen2.py
pixaris/generation/utils.py
pixaris/metrics/__init__.py
pixaris/metrics/base.py
pixaris/metrics/iou.py
pixaris/metrics/llm.py
pixaris/metrics/luminescence.py
pixaris/metrics/prompts.py
pixaris/metrics/saturation.py
pixaris/metrics/utils.py
pixaris/orchestration/__init__.py
pixaris/orchestration/base.py
pixaris/orchestration/kubernetes.py
pixaris/utils/__init__.py
pixaris/utils/bigquery.py
pixaris/utils/hyperparameters.py
pixaris/utils/merge_dicts.py
pixaris/utils/retry.py
pixaris-0.9.0.dist-info/METADATA
pixaris-0.9.0.dist-info/WHEEL
pixaris-0.9.0.dist-info/entry_points.txt
pixaris-0.9.0.dist-info/licenses/LICENSE
pixaris-0.9.0.dist-info/RECORD
