Metadata-Version: 2.4
Name: pixaris
Version: 0.9.0
Summary: Evaluation framework for image generation
License-File: LICENSE
Author: Team TIGA
Requires-Python: >=3.12,<4.0
Classifier: Programming Language :: Python :: 3
Classifier: Programming Language :: Python :: 3.12
Classifier: Programming Language :: Python :: 3.13
Classifier: Programming Language :: Python :: 3.14
Requires-Dist: brotli (>=1.1.0,<2.0.0)
Requires-Dist: click (>=8.1.8,<9.0.0)
Requires-Dist: db-dtypes (>=1.4.2,<2.0.0)
Requires-Dist: decorator (==5.2.1)
Requires-Dist: gradio (>=5.22.0,<6.0.0)
Requires-Dist: pillow (>=11.3.0)
Requires-Dist: scikit-learn (>=1.6.1,<2.0.0)
Requires-Dist: starlette (>=0.47.2)
Requires-Dist: urllib3 (>=0.5.0)
